<?xml version="1.0" encoding="UTF-8"?>
<!-- generated on 2019-01-21 01:54:26.709764 by $Id$
  options: 
-->
<routes xmlns:xsi="http://www.w3.org/2001/XMLSchema-instance" xsi:noNamespaceSchemaLocation="http://sumo.dlr.de/xsd/routes_file.xsd">
    <person id="p40" depart="4.00" departPos="random">
        <walk from="WC" to="EC" arrivalPos="random"/>
    </person>
    <person id="p41" depart="5.00" departPos="random">
        <walk from="WC" to="EC" arrivalPos="random"/>
    </person>
    <person id="p42" depart="7.00" departPos="random">
        <walk from="WC" to="EC" arrivalPos="random"/>
    </person>
    <person id="p43" depart="8.00" departPos="random">
        <walk from="WC" to="EC" arrivalPos="random"/>
    </person>
    <person id="p44" depart="9.00" departPos="random">
        <walk from="WC" to="EC" arrivalPos="random"/>
    </person>
    <person id="p45" depart="10.00" departPos="random">
        <walk from="WC" to="EC" arrivalPos="random"/>
    </person>
    <person id="p46" depart="11.00" departPos="random">
        <walk from="WC" to="EC" arrivalPos="random"/>
    </person>
    <person id="p47" depart="11.00" departPos="random">
        <walk from="WC" to="EC" arrivalPos="random"/>
    </person>
    <person id="p48" depart="11.00" departPos="random">
        <walk from="WC" to="EC" arrivalPos="random"/>
    </person>
    <person id="p49" depart="12.00" departPos="random">
        <walk from="WC" to="EC" arrivalPos="random"/>
    </person>
    <person id="p410" depart="12.00" departPos="random">
        <walk from="WC" to="EC" arrivalPos="random"/>
    </person>
    <person id="p411" depart="12.00" departPos="random">
        <walk from="WC" to="EC" arrivalPos="random"/>
    </person>
    <person id="p412" depart="12.00" departPos="random">
        <walk from="WC" to="EC" arrivalPos="random"/>
    </person>
    <person id="p413" depart="13.00" departPos="random">
        <walk from="WC" to="EC" arrivalPos="random"/>
    </person>
    <person id="p414" depart="13.00" departPos="random">
        <walk from="WC" to="EC" arrivalPos="random"/>
    </person>
    <person id="p415" depart="13.00" departPos="random">
        <walk from="WC" to="EC" arrivalPos="random"/>
    </person>
    <person id="p416" depart="14.00" departPos="random">
        <walk from="WC" to="EC" arrivalPos="random"/>
    </person>
    <person id="p417" depart="14.00" departPos="random">
        <walk from="WC" to="EC" arrivalPos="random"/>
    </person>
    <person id="p418" depart="14.00" departPos="random">
        <walk from="WC" to="EC" arrivalPos="random"/>
    </person>
    <person id="p419" depart="15.00" departPos="random">
        <walk from="WC" to="EC" arrivalPos="random"/>
    </person>
    <person id="p420" depart="15.00" departPos="random">
        <walk from="WC" to="EC" arrivalPos="random"/>
    </person>
    <person id="p421" depart="16.00" departPos="random">
        <walk from="WC" to="EC" arrivalPos="random"/>
    </person>
    <person id="p422" depart="16.00" departPos="random">
        <walk from="WC" to="EC" arrivalPos="random"/>
    </person>
    <person id="p423" depart="17.00" departPos="random">
        <walk from="WC" to="EC" arrivalPos="random"/>
    </person>
    <person id="p424" depart="17.00" departPos="random">
        <walk from="WC" to="EC" arrivalPos="random"/>
    </person>
    <person id="p425" depart="20.00" departPos="random">
        <walk from="WC" to="EC" arrivalPos="random"/>
    </person>
    <person id="p426" depart="20.00" departPos="random">
        <walk from="WC" to="EC" arrivalPos="random"/>
    </person>
    <person id="p427" depart="20.00" departPos="random">
        <walk from="WC" to="EC" arrivalPos="random"/>
    </person>
    <person id="p428" depart="20.00" departPos="random">
        <walk from="WC" to="EC" arrivalPos="random"/>
    </person>
    <person id="p429" depart="21.00" departPos="random">
        <walk from="WC" to="EC" arrivalPos="random"/>
    </person>
    <person id="p430" depart="21.00" departPos="random">
        <walk from="WC" to="EC" arrivalPos="random"/>
    </person>
    <person id="p431" depart="22.00" departPos="random">
        <walk from="WC" to="EC" arrivalPos="random"/>
    </person>
    <person id="p432" depart="23.00" departPos="random">
        <walk from="WC" to="EC" arrivalPos="random"/>
    </person>
    <person id="p433" depart="24.00" departPos="random">
        <walk from="WC" to="EC" arrivalPos="random"/>
    </person>
    <person id="p434" depart="25.00" departPos="random">
        <walk from="WC" to="EC" arrivalPos="random"/>
    </person>
    <person id="p435" depart="26.00" departPos="random">
        <walk from="WC" to="EC" arrivalPos="random"/>
    </person>
    <person id="p436" depart="27.00" departPos="random">
        <walk from="WC" to="EC" arrivalPos="random"/>
    </person>
    <person id="p437" depart="28.00" departPos="random">
        <walk from="WC" to="EC" arrivalPos="random"/>
    </person>
    <person id="p438" depart="29.00" departPos="random">
        <walk from="WC" to="EC" arrivalPos="random"/>
    </person>
    <person id="p439" depart="30.00" departPos="random">
        <walk from="WC" to="EC" arrivalPos="random"/>
    </person>
    <person id="p440" depart="30.00" departPos="random">
        <walk from="WC" to="EC" arrivalPos="random"/>
    </person>
    <person id="p441" depart="30.00" departPos="random">
        <walk from="WC" to="EC" arrivalPos="random"/>
    </person>
    <person id="p442" depart="31.00" departPos="random">
        <walk from="WC" to="EC" arrivalPos="random"/>
    </person>
    <person id="p443" depart="31.00" departPos="random">
        <walk from="WC" to="EC" arrivalPos="random"/>
    </person>
    <person id="p444" depart="1761.00" departPos="random">
        <walk from="WC" to="EC" arrivalPos="random"/>
    </person>
    <person id="p445" depart="1761.00" departPos="random">
        <walk from="WC" to="EC" arrivalPos="random"/>
    </person>
    <person id="p446" depart="1770.00" departPos="random">
        <walk from="WC" to="EC" arrivalPos="random"/>
    </person>
    <person id="p447" depart="1791.00" departPos="random">
        <walk from="WC" to="EC" arrivalPos="random"/>
    </person>
    <person id="p448" depart="1819.00" departPos="random">
        <walk from="WC" to="EC" arrivalPos="random"/>
    </person>
    <person id="p449" depart="1901.00" departPos="random">
        <walk from="WC" to="EC" arrivalPos="random"/>
    </person>
    <person id="p450" depart="1927.00" departPos="random">
        <walk from="WC" to="EC" arrivalPos="random"/>
    </person>
    <person id="p451" depart="1958.00" departPos="random">
        <walk from="WC" to="EC" arrivalPos="random"/>
    </person>
    <person id="p452" depart="1997.00" departPos="random">
        <walk from="WC" to="EC" arrivalPos="random"/>
    </person>
    <person id="p453" depart="2038.00" departPos="random">
        <walk from="WC" to="EC" arrivalPos="random"/>
    </person>
    <person id="p454" depart="2084.00" departPos="random">
        <walk from="WC" to="EC" arrivalPos="random"/>
    </person>
    <person id="p455" depart="2136.00" departPos="random">
        <walk from="WC" to="EC" arrivalPos="random"/>
    </person>
    <person id="p456" depart="2169.00" departPos="random">
        <walk from="WC" to="EC" arrivalPos="random"/>
    </person>
    <person id="p457" depart="2178.00" departPos="random">
        <walk from="WC" to="EC" arrivalPos="random"/>
    </person>
    <person id="p458" depart="2250.00" departPos="random">
        <walk from="WC" to="EC" arrivalPos="random"/>
    </person>
    <person id="p459" depart="2386.00" departPos="random">
        <walk from="WC" to="EC" arrivalPos="random"/>
    </person>
    <person id="p460" depart="2401.00" departPos="random">
        <walk from="WC" to="EC" arrivalPos="random"/>
    </person>
    <person id="p461" depart="2407.00" departPos="random">
        <walk from="WC" to="EC" arrivalPos="random"/>
    </person>
    <person id="p462" depart="2407.00" departPos="random">
        <walk from="WC" to="EC" arrivalPos="random"/>
    </person>
    <person id="p463" depart="2552.00" departPos="random">
        <walk from="WC" to="EC" arrivalPos="random"/>
    </person>
    <person id="p464" depart="2566.00" departPos="random">
        <walk from="WC" to="EC" arrivalPos="random"/>
    </person>
    <person id="p465" depart="2608.00" departPos="random">
        <walk from="WC" to="EC" arrivalPos="random"/>
    </person>
    <person id="p466" depart="2646.00" departPos="random">
        <walk from="WC" to="EC" arrivalPos="random"/>
    </person>
    <person id="p467" depart="2661.00" departPos="random">
        <walk from="WC" to="EC" arrivalPos="random"/>
    </person>
    <person id="p468" depart="2691.00" departPos="random">
        <walk from="WC" to="EC" arrivalPos="random"/>
    </person>
    <person id="p469" depart="2770.00" departPos="random">
        <walk from="WC" to="EC" arrivalPos="random"/>
    </person>
    <person id="p470" depart="2811.00" departPos="random">
        <walk from="WC" to="EC" arrivalPos="random"/>
    </person>
    <person id="p471" depart="2857.00" departPos="random">
        <walk from="WC" to="EC" arrivalPos="random"/>
    </person>
    <person id="p472" depart="2923.00" departPos="random">
        <walk from="WC" to="EC" arrivalPos="random"/>
    </person>
    <person id="p473" depart="2994.00" departPos="random">
        <walk from="WC" to="EC" arrivalPos="random"/>
    </person>
    <person id="p474" depart="3005.00" departPos="random">
        <walk from="WC" to="EC" arrivalPos="random"/>
    </person>
    <person id="p475" depart="3034.00" departPos="random">
        <walk from="WC" to="EC" arrivalPos="random"/>
    </person>
    <person id="p476" depart="3124.00" departPos="random">
        <walk from="WC" to="EC" arrivalPos="random"/>
    </person>
    <person id="p477" depart="3128.00" departPos="random">
        <walk from="WC" to="EC" arrivalPos="random"/>
    </person>
    <person id="p478" depart="3212.00" departPos="random">
        <walk from="WC" to="EC" arrivalPos="random"/>
    </person>
    <person id="p479" depart="3246.00" departPos="random">
        <walk from="WC" to="EC" arrivalPos="random"/>
    </person>
    <person id="p480" depart="3269.00" departPos="random">
        <walk from="WC" to="EC" arrivalPos="random"/>
    </person>
    <person id="p481" depart="3316.00" departPos="random">
        <walk from="WC" to="EC" arrivalPos="random"/>
    </person>
    <person id="p482" depart="3364.00" departPos="random">
        <walk from="WC" to="EC" arrivalPos="random"/>
    </person>
    <person id="p483" depart="3393.00" departPos="random">
        <walk from="WC" to="EC" arrivalPos="random"/>
    </person>
    <person id="p484" depart="3415.00" departPos="random">
        <walk from="WC" to="EC" arrivalPos="random"/>
    </person>
    <person id="p485" depart="3443.00" departPos="random">
        <walk from="WC" to="EC" arrivalPos="random"/>
    </person>
    <person id="p486" depart="3466.00" departPos="random">
        <walk from="WC" to="EC" arrivalPos="random"/>
    </person>
    <person id="p487" depart="3480.00" departPos="random">
        <walk from="WC" to="EC" arrivalPos="random"/>
    </person>
    <person id="p488" depart="3506.00" departPos="random">
        <walk from="WC" to="EC" arrivalPos="random"/>
    </person>
    <person id="p489" depart="3536.00" departPos="random">
        <walk from="WC" to="EC" arrivalPos="random"/>
    </person>
    <person id="p490" depart="3537.00" departPos="random">
        <walk from="WC" to="EC" arrivalPos="random"/>
    </person>
    <person id="p491" depart="3553.00" departPos="random">
        <walk from="WC" to="EC" arrivalPos="random"/>
    </person>
    <person id="p492" depart="3594.00" departPos="random">
        <walk from="WC" to="EC" arrivalPos="random"/>
    </person>

</routes>
